OneBotConnecter/MessageType.py
OneBotConnecter/OneBot.py
OneBotConnecter/__init__.py
onebotconnecter-0.2.20.dist-info/licenses/LICENSE
onebotconnecter-0.2.20.dist-info/METADATA
onebotconnecter-0.2.20.dist-info/WHEEL
onebotconnecter-0.2.20.dist-info/top_level.txt
onebotconnecter-0.2.20.dist-info/RECORD
