Metadata-Version: 2.4
Name: OneBotConnecter
Version: 0.2.20
Summary: 基于websocket(服务器正向)连接的onebot11通用python接口
Author-email: Sugar51243 <1733682365@qq.com>
License: MIT License
Project-URL: Homepage, https://github.com/Sugar51243/OneBotConnecter
Project-URL: Issues, https://github.com/Sugar51243/OneBotConnecter/issues
Classifier: Programming Language :: Python :: 3
Classifier: Operating System :: OS Independent
Requires-Python: >=3.9
License-File: LICENSE
Dynamic: license-file
